pyalby/__init__.py
pyalby/account.py
pyalby/invoice.py
pyalby/payment.py
pyalby/utils.py
pyalby-0.0.1.dist-info/LICENSE
pyalby-0.0.1.dist-info/METADATA
pyalby-0.0.1.dist-info/WHEEL
pyalby-0.0.1.dist-info/top_level.txt
pyalby-0.0.1.dist-info/RECORD
