Metadata-Version: 2.1
Name: pyalby
Version: 0.0.1
Summary: Python library for Alby Wallet API
Author-email: Felix Frei <felix.frei@gmx.ch>
Maintainer-email: Felix Frei <felix.frei@gmx.ch>
License: MIT License
Project-URL: Repository, https://github.com/f418me/pyalby.git
Project-URL: Bug Tracker, https://github.com/f418me/pyalby/issues
Classifier: Programming Language :: Python :: 3
Classifier: Operating System :: OS Independent
Requires-Python: <3.12,>=3.10
License-File: LICENSE
Requires-Dist: requests ==2.31.0
Requires-Dist: python-dotenv ==1.0.1
Requires-Dist: responses ==0.25.0
